package  com/kaspersky/zeronights2017/nightwatcher;

super public class MainActivity
	extends android/app/Activity
	version 50:0
{

public static Field a:"Landroid/widget/EditText;";
public static Field b:"Landroid/widget/EditText;";
public static Field c:"Ljava/lang/String;";
private Field d:"Ljava/lang/String;";
private final Field e:"Ljava/lang/String;";

public Method "<init>":"()V"
	stack 2 locals 1
{
		aload_0;
		invokespecial	Method android/app/Activity."<init>":"()V";
		aload_0;
		getstatic	Field "\uFEFF\uFEFF\uFEFF\uFEFF\uFEFF\uFEFF\uFEFF\uFEFF\uFEFF\uFEFF\uFEFF\uFEFF\uFEFF\uFEFF".q:"Ljava/lang/String;";
		putfield	Field d:"Ljava/lang/String;";
		aload_0;
		getstatic	Field "\uFEFF\uFEFF\uFEFF\uFEFF\uFEFF\uFEFF\uFEFF\uFEFF\uFEFF\uFEFF\uFEFF\uFEFF\uFEFF\uFEFF".d:"Ljava/lang/String;";
		invokestatic	Method "\uFEFF\uFEFF\uFEFF\uFEFF\uFEFF\uFEFF\uFEFF\uFEFF\uFEFF\uFEFF\uFEFF\uFEFF\uFEFF\uFEFF\uFEFF\uFEFF"."\uFEFF\uFEFF\uFEFF\uFEFF\uFEFF\uFEFF\uFEFF\uFEFF\uFEFF\uFEFF\uFEFF\uFEFF\uFEFF\uFEFF\uFEFF\uFEFF\uFEFF\uFEFF\uFEFF\uFEFF\uFEFF\uFEFF\uFEFF\uFEFF\uFEFF\uFEFF\uFEFF\uFEFF\uFEFF\uFEFF\uFEFF\uFEFF\uFEFF\uFEFF\uFEFF\uFEFF\uFEFF\uFEFF\uFEFF\uFEFF\uFEFF\uFEFF\uFEFF\uFEFF\uFEFF\uFEFF\uFEFF\uFEFF\uFEFF\uFEFF\uFEFF\uFEFF\uFEFF\uFEFF\uFEFF\uFEFF\uFEFF\uFEFF\uFEFF\uFEFF\uFEFF\uFEFF":"(Ljava/lang/String;)Ljava/lang/String;";
		putfield	Field e:"Ljava/lang/String;";
		return;
}

private Method a:"()V"
	stack 5 locals 3
{
		aload_0;
		invokevirtual	Method getResources:"()Landroid/content/res/Resources;";
		ldc	int 2131099746;
		invokestatic	Method android/graphics/BitmapFactory.decodeResource:"(Landroid/content/res/Resources;I)Landroid/graphics/Bitmap;";
		astore_1;
		getstatic	Field android/os/Build$VERSION.SDK_INT:"I";
		bipush	19;
		if_icmple	L278;
		aload_0;
		new	class java/lang/StringBuilder;
		dup;
		invokespecial	Method java/lang/StringBuilder."<init>":"()V";
		aload_0;
		invokevirtual	Method getFilesDir:"()Ljava/io/File;";
		invokevirtual	Method java/lang/StringBuilder.append:"(Ljava/lang/Object;)Ljava/lang/StringBuilder;";
		getstatic	Field "\uFEFF\uFEFF\uFEFF\uFEFF\uFEFF\uFEFF\uFEFF\uFEFF\uFEFF\uFEFF\uFEFF\uFEFF\uFEFF\uFEFF".e:"Ljava/lang/String;";
		invokevirtual	Method java/lang/StringBuilder.append:"(Ljava/lang/String;)Ljava/lang/StringBuilder;";
		invokevirtual	Method java/lang/StringBuilder.toString:"()Ljava/lang/String;";
		putfield	Field d:"Ljava/lang/String;";
		new	class com/googlecode/tesseract/android/TessBaseAPI;
		dup;
		invokespecial	Method com/googlecode/tesseract/android/TessBaseAPI."<init>":"()V";
		astore_2;
		aload_0;
		new	class java/io/File;
		dup;
		new	class java/lang/StringBuilder;
		dup;
		invokespecial	Method java/lang/StringBuilder."<init>":"()V";
		aload_0;
		getfield	Field d:"Ljava/lang/String;";
		invokevirtual	Method java/lang/StringBuilder.append:"(Ljava/lang/String;)Ljava/lang/StringBuilder;";
		aload_0;
		getfield	Field e:"Ljava/lang/String;";
		invokevirtual	Method java/lang/StringBuilder.append:"(Ljava/lang/String;)Ljava/lang/StringBuilder;";
		invokevirtual	Method java/lang/StringBuilder.toString:"()Ljava/lang/String;";
		invokespecial	Method java/io/File."<init>":"(Ljava/lang/String;)V";
		getstatic	Field "\uFEFF\uFEFF\uFEFF\uFEFF\uFEFF\uFEFF\uFEFF\uFEFF\uFEFF\uFEFF\uFEFF\uFEFF\uFEFF\uFEFF".i:"Ljava/lang/String;";
		invokespecial	Method a:"(Ljava/io/File;Ljava/lang/String;)V";
		aload_2;
		aload_0;
		getfield	Field d:"Ljava/lang/String;";
		getstatic	Field "\uFEFF\uFEFF\uFEFF\uFEFF\uFEFF\uFEFF\uFEFF\uFEFF\uFEFF\uFEFF\uFEFF\uFEFF\uFEFF\uFEFF".f:"Ljava/lang/String;";
		invokevirtual	Method com/googlecode/tesseract/android/TessBaseAPI.a:"(Ljava/lang/String;Ljava/lang/String;)Z";
		pop;
		aload_2;
		aload_1;
		invokevirtual	Method com/googlecode/tesseract/android/TessBaseAPI.a:"(Landroid/graphics/Bitmap;)V";
		aload_2;
		invokevirtual	Method com/googlecode/tesseract/android/TessBaseAPI.a:"()Ljava/lang/String;";
		putstatic	Field c:"Ljava/lang/String;";
		aload_0;
		new	class java/io/File;
		dup;
		new	class java/lang/StringBuilder;
		dup;
		invokespecial	Method java/lang/StringBuilder."<init>":"()V";
		aload_0;
		getfield	Field d:"Ljava/lang/String;";
		invokevirtual	Method java/lang/StringBuilder.append:"(Ljava/lang/String;)Ljava/lang/StringBuilder;";
		aload_0;
		getfield	Field e:"Ljava/lang/String;";
		invokevirtual	Method java/lang/StringBuilder.append:"(Ljava/lang/String;)Ljava/lang/StringBuilder;";
		invokevirtual	Method java/lang/StringBuilder.toString:"()Ljava/lang/String;";
		invokespecial	Method java/io/File."<init>":"(Ljava/lang/String;)V";
		getstatic	Field "\uFEFF\uFEFF\uFEFF\uFEFF\uFEFF\uFEFF\uFEFF\uFEFF\uFEFF\uFEFF\uFEFF\uFEFF\uFEFF\uFEFF".j:"Ljava/lang/String;";
		invokespecial	Method a:"(Ljava/io/File;Ljava/lang/String;)V";
		aload_2;
		aload_0;
		getfield	Field d:"Ljava/lang/String;";
		getstatic	Field "\uFEFF\uFEFF\uFEFF\uFEFF\uFEFF\uFEFF\uFEFF\uFEFF\uFEFF\uFEFF\uFEFF\uFEFF\uFEFF\uFEFF".g:"Ljava/lang/String;";
		invokevirtual	Method com/googlecode/tesseract/android/TessBaseAPI.a:"(Ljava/lang/String;Ljava/lang/String;)Z";
		pop;
		aload_2;
		aload_1;
		invokevirtual	Method com/googlecode/tesseract/android/TessBaseAPI.a:"(Landroid/graphics/Bitmap;)V";
		new	class java/lang/StringBuilder;
		dup;
		invokespecial	Method java/lang/StringBuilder."<init>":"()V";
		getstatic	Field c:"Ljava/lang/String;";
		invokevirtual	Method java/lang/StringBuilder.append:"(Ljava/lang/String;)Ljava/lang/StringBuilder;";
		aload_2;
		invokevirtual	Method com/googlecode/tesseract/android/TessBaseAPI.a:"()Ljava/lang/String;";
		invokevirtual	Method java/lang/StringBuilder.append:"(Ljava/lang/String;)Ljava/lang/StringBuilder;";
		invokevirtual	Method java/lang/StringBuilder.toString:"()Ljava/lang/String;";
		putstatic	Field c:"Ljava/lang/String;";
		aload_0;
		new	class java/io/File;
		dup;
		new	class java/lang/StringBuilder;
		dup;
		invokespecial	Method java/lang/StringBuilder."<init>":"()V";
		aload_0;
		getfield	Field d:"Ljava/lang/String;";
		invokevirtual	Method java/lang/StringBuilder.append:"(Ljava/lang/String;)Ljava/lang/StringBuilder;";
		aload_0;
		getfield	Field e:"Ljava/lang/String;";
		invokevirtual	Method java/lang/StringBuilder.append:"(Ljava/lang/String;)Ljava/lang/StringBuilder;";
		invokevirtual	Method java/lang/StringBuilder.toString:"()Ljava/lang/String;";
		invokespecial	Method java/io/File."<init>":"(Ljava/lang/String;)V";
		getstatic	Field "\uFEFF\uFEFF\uFEFF\uFEFF\uFEFF\uFEFF\uFEFF\uFEFF\uFEFF\uFEFF\uFEFF\uFEFF\uFEFF\uFEFF".k:"Ljava/lang/String;";
		invokespecial	Method a:"(Ljava/io/File;Ljava/lang/String;)V";
		aload_2;
		aload_0;
		getfield	Field d:"Ljava/lang/String;";
		getstatic	Field "\uFEFF\uFEFF\uFEFF\uFEFF\uFEFF\uFEFF\uFEFF\uFEFF\uFEFF\uFEFF\uFEFF\uFEFF\uFEFF\uFEFF".h:"Ljava/lang/String;";
		invokevirtual	Method com/googlecode/tesseract/android/TessBaseAPI.a:"(Ljava/lang/String;Ljava/lang/String;)Z";
		pop;
		aload_2;
		aload_1;
		invokevirtual	Method com/googlecode/tesseract/android/TessBaseAPI.a:"(Landroid/graphics/Bitmap;)V";
		new	class java/lang/StringBuilder;
		dup;
		invokespecial	Method java/lang/StringBuilder."<init>":"()V";
		getstatic	Field c:"Ljava/lang/String;";
		invokevirtual	Method java/lang/StringBuilder.append:"(Ljava/lang/String;)Ljava/lang/StringBuilder;";
		aload_2;
		invokevirtual	Method com/googlecode/tesseract/android/TessBaseAPI.a:"()Ljava/lang/String;";
		invokevirtual	Method java/lang/StringBuilder.append:"(Ljava/lang/String;)Ljava/lang/StringBuilder;";
		invokevirtual	Method java/lang/StringBuilder.toString:"()Ljava/lang/String;";
		putstatic	Field c:"Ljava/lang/String;";
	L277:
		return;
	L278:
		aload_0;
		new	class java/lang/StringBuilder;
		dup;
		invokespecial	Method java/lang/StringBuilder."<init>":"()V";
		aload_0;
		invokevirtual	Method getFilesDir:"()Ljava/io/File;";
		invokevirtual	Method java/lang/StringBuilder.append:"(Ljava/lang/Object;)Ljava/lang/StringBuilder;";
		getstatic	Field "\uFEFF\uFEFF\uFEFF\uFEFF\uFEFF\uFEFF\uFEFF\uFEFF\uFEFF\uFEFF\uFEFF\uFEFF\uFEFF\uFEFF".e:"Ljava/lang/String;";
		invokevirtual	Method java/lang/StringBuilder.append:"(Ljava/lang/String;)Ljava/lang/StringBuilder;";
		invokevirtual	Method java/lang/StringBuilder.toString:"()Ljava/lang/String;";
		putfield	Field d:"Ljava/lang/String;";
		new	class com/googlecode/tesseract/android/TessBaseAPI;
		dup;
		invokespecial	Method com/googlecode/tesseract/android/TessBaseAPI."<init>":"()V";
		astore_2;
		aload_0;
		new	class java/io/File;
		dup;
		new	class java/lang/StringBuilder;
		dup;
		invokespecial	Method java/lang/StringBuilder."<init>":"()V";
		aload_0;
		getfield	Field d:"Ljava/lang/String;";
		invokevirtual	Method java/lang/StringBuilder.append:"(Ljava/lang/String;)Ljava/lang/StringBuilder;";
		aload_0;
		getfield	Field e:"Ljava/lang/String;";
		invokevirtual	Method java/lang/StringBuilder.append:"(Ljava/lang/String;)Ljava/lang/StringBuilder;";
		invokevirtual	Method java/lang/StringBuilder.toString:"()Ljava/lang/String;";
		invokespecial	Method java/io/File."<init>":"(Ljava/lang/String;)V";
		getstatic	Field "\uFEFF\uFEFF\uFEFF\uFEFF\uFEFF\uFEFF\uFEFF\uFEFF\uFEFF\uFEFF\uFEFF\uFEFF\uFEFF\uFEFF".i:"Ljava/lang/String;";
		invokespecial	Method a:"(Ljava/io/File;Ljava/lang/String;)V";
		aload_2;
		aload_0;
		getfield	Field d:"Ljava/lang/String;";
		getstatic	Field "\uFEFF\uFEFF\uFEFF\uFEFF\uFEFF\uFEFF\uFEFF\uFEFF\uFEFF\uFEFF\uFEFF\uFEFF\uFEFF\uFEFF".f:"Ljava/lang/String;";
		invokevirtual	Method com/googlecode/tesseract/android/TessBaseAPI.a:"(Ljava/lang/String;Ljava/lang/String;)Z";
		pop;
		aload_2;
		aload_1;
		invokevirtual	Method com/googlecode/tesseract/android/TessBaseAPI.a:"(Landroid/graphics/Bitmap;)V";
		aload_2;
		invokevirtual	Method com/googlecode/tesseract/android/TessBaseAPI.a:"()Ljava/lang/String;";
		ldc	String "\n";
		invokevirtual	Method java/lang/String.split:"(Ljava/lang/String;)[Ljava/lang/String;";
		iconst_0;
		aaload;
		putstatic	Field c:"Ljava/lang/String;";
		aload_0;
		new	class java/io/File;
		dup;
		new	class java/lang/StringBuilder;
		dup;
		invokespecial	Method java/lang/StringBuilder."<init>":"()V";
		aload_0;
		getfield	Field d:"Ljava/lang/String;";
		invokevirtual	Method java/lang/StringBuilder.append:"(Ljava/lang/String;)Ljava/lang/StringBuilder;";
		aload_0;
		getfield	Field e:"Ljava/lang/String;";
		invokevirtual	Method java/lang/StringBuilder.append:"(Ljava/lang/String;)Ljava/lang/StringBuilder;";
		invokevirtual	Method java/lang/StringBuilder.toString:"()Ljava/lang/String;";
		invokespecial	Method java/io/File."<init>":"(Ljava/lang/String;)V";
		getstatic	Field "\uFEFF\uFEFF\uFEFF\uFEFF\uFEFF\uFEFF\uFEFF\uFEFF\uFEFF\uFEFF\uFEFF\uFEFF\uFEFF\uFEFF".j:"Ljava/lang/String;";
		invokespecial	Method a:"(Ljava/io/File;Ljava/lang/String;)V";
		aload_2;
		aload_0;
		getfield	Field d:"Ljava/lang/String;";
		getstatic	Field "\uFEFF\uFEFF\uFEFF\uFEFF\uFEFF\uFEFF\uFEFF\uFEFF\uFEFF\uFEFF\uFEFF\uFEFF\uFEFF\uFEFF".g:"Ljava/lang/String;";
		invokevirtual	Method com/googlecode/tesseract/android/TessBaseAPI.a:"(Ljava/lang/String;Ljava/lang/String;)Z";
		pop;
		aload_2;
		aload_1;
		invokevirtual	Method com/googlecode/tesseract/android/TessBaseAPI.a:"(Landroid/graphics/Bitmap;)V";
		new	class java/lang/StringBuilder;
		dup;
		invokespecial	Method java/lang/StringBuilder."<init>":"()V";
		getstatic	Field c:"Ljava/lang/String;";
		invokevirtual	Method java/lang/StringBuilder.append:"(Ljava/lang/String;)Ljava/lang/StringBuilder;";
		aload_2;
		invokevirtual	Method com/googlecode/tesseract/android/TessBaseAPI.a:"()Ljava/lang/String;";
		ldc	String "\n";
		invokevirtual	Method java/lang/String.split:"(Ljava/lang/String;)[Ljava/lang/String;";
		iconst_0;
		aaload;
		invokevirtual	Method java/lang/StringBuilder.append:"(Ljava/lang/String;)Ljava/lang/StringBuilder;";
		invokevirtual	Method java/lang/StringBuilder.toString:"()Ljava/lang/String;";
		putstatic	Field c:"Ljava/lang/String;";
		aload_0;
		new	class java/io/File;
		dup;
		new	class java/lang/StringBuilder;
		dup;
		invokespecial	Method java/lang/StringBuilder."<init>":"()V";
		aload_0;
		getfield	Field d:"Ljava/lang/String;";
		invokevirtual	Method java/lang/StringBuilder.append:"(Ljava/lang/String;)Ljava/lang/StringBuilder;";
		aload_0;
		getfield	Field e:"Ljava/lang/String;";
		invokevirtual	Method java/lang/StringBuilder.append:"(Ljava/lang/String;)Ljava/lang/StringBuilder;";
		invokevirtual	Method java/lang/StringBuilder.toString:"()Ljava/lang/String;";
		invokespecial	Method java/io/File."<init>":"(Ljava/lang/String;)V";
		getstatic	Field "\uFEFF\uFEFF\uFEFF\uFEFF\uFEFF\uFEFF\uFEFF\uFEFF\uFEFF\uFEFF\uFEFF\uFEFF\uFEFF\uFEFF".k:"Ljava/lang/String;";
		invokespecial	Method a:"(Ljava/io/File;Ljava/lang/String;)V";
		aload_2;
		aload_0;
		getfield	Field d:"Ljava/lang/String;";
		getstatic	Field "\uFEFF\uFEFF\uFEFF\uFEFF\uFEFF\uFEFF\uFEFF\uFEFF\uFEFF\uFEFF\uFEFF\uFEFF\uFEFF\uFEFF".h:"Ljava/lang/String;";
		invokevirtual	Method com/googlecode/tesseract/android/TessBaseAPI.a:"(Ljava/lang/String;Ljava/lang/String;)Z";
		pop;
		aload_2;
		aload_1;
		invokevirtual	Method com/googlecode/tesseract/android/TessBaseAPI.a:"(Landroid/graphics/Bitmap;)V";
		new	class java/lang/StringBuilder;
		dup;
		invokespecial	Method java/lang/StringBuilder."<init>":"()V";
		getstatic	Field c:"Ljava/lang/String;";
		invokevirtual	Method java/lang/StringBuilder.append:"(Ljava/lang/String;)Ljava/lang/StringBuilder;";
		aload_2;
		invokevirtual	Method com/googlecode/tesseract/android/TessBaseAPI.a:"()Ljava/lang/String;";
		ldc	String "\n";
		invokevirtual	Method java/lang/String.split:"(Ljava/lang/String;)[Ljava/lang/String;";
		iconst_0;
		aaload;
		invokevirtual	Method java/lang/StringBuilder.append:"(Ljava/lang/String;)Ljava/lang/StringBuilder;";
		invokevirtual	Method java/lang/StringBuilder.toString:"()Ljava/lang/String;";
		putstatic	Field c:"Ljava/lang/String;";
		goto	L277;
}

static synthetic Method a:"(Lcom/kaspersky/zeronights2017/nightwatcher/MainActivity;)V"
	stack 1 locals 1
{
		aload_0;
		invokespecial	Method a:"()V";
		return;
}

private Method a:"(Ljava/io/File;Ljava/lang/String;)V"
	stack 4 locals 3
{
		aload_1;
		invokevirtual	Method java/io/File.exists:"()Z";
		ifne	L19;
		aload_1;
		invokevirtual	Method java/io/File.mkdirs:"()Z";
		ifeq	L19;
		aload_0;
		aload_2;
		invokespecial	Method a:"(Ljava/lang/String;)V";
	L19:
		aload_1;
		invokevirtual	Method java/io/File.exists:"()Z";
		ifeq	L72;
		new	class java/io/File;
		dup;
		new	class java/lang/StringBuilder;
		dup;
		invokespecial	Method java/lang/StringBuilder."<init>":"()V";
		aload_0;
		getfield	Field d:"Ljava/lang/String;";
		invokevirtual	Method java/lang/StringBuilder.append:"(Ljava/lang/String;)Ljava/lang/StringBuilder;";
		aload_0;
		getfield	Field e:"Ljava/lang/String;";
		invokevirtual	Method java/lang/StringBuilder.append:"(Ljava/lang/String;)Ljava/lang/StringBuilder;";
		aload_2;
		invokevirtual	Method java/lang/StringBuilder.append:"(Ljava/lang/String;)Ljava/lang/StringBuilder;";
		invokevirtual	Method java/lang/StringBuilder.toString:"()Ljava/lang/String;";
		invokespecial	Method java/io/File."<init>":"(Ljava/lang/String;)V";
		invokevirtual	Method java/io/File.exists:"()Z";
		ifne	L72;
		aload_0;
		aload_2;
		invokespecial	Method a:"(Ljava/lang/String;)V";
	L72:
		return;
}

private Method a:"(Ljava/lang/String;)V"
	stack 4 locals 8
{
		aload_1;
		astore	4;

	try t0;
		new	class java/lang/StringBuilder;
		astore	5;

		aload_1;
		astore	4;

		aload	5;
		invokespecial	Method java/lang/StringBuilder."<init>":"()V";

		aload_1;
		astore	4;

		aload	5;
		aload_0;
		getfield	Field d:"Ljava/lang/String;";
		invokevirtual	Method java/lang/StringBuilder.append:"(Ljava/lang/String;)Ljava/lang/StringBuilder;";
		aload_0;
		getfield	Field e:"Ljava/lang/String;";
		invokevirtual	Method java/lang/StringBuilder.append:"(Ljava/lang/String;)Ljava/lang/StringBuilder;";
		aload_1;
		invokestatic	Method "\uFEFF\uFEFF\uFEFF\uFEFF\uFEFF\uFEFF\uFEFF\uFEFF\uFEFF\uFEFF\uFEFF\uFEFF\uFEFF\uFEFF\uFEFF\uFEFF"."\uFEFF\uFEFF\uFEFF\uFEFF\uFEFF\uFEFF\uFEFF\uFEFF\uFEFF\uFEFF\uFEFF\uFEFF\uFEFF\uFEFF\uFEFF\uFEFF\uFEFF\uFEFF\uFEFF\uFEFF\uFEFF\uFEFF\uFEFF\uFEFF\uFEFF\uFEFF\uFEFF\uFEFF\uFEFF\uFEFF\uFEFF\uFEFF\uFEFF\uFEFF\uFEFF\uFEFF\uFEFF\uFEFF\uFEFF\uFEFF\uFEFF\uFEFF\uFEFF\uFEFF\uFEFF\uFEFF\uFEFF\uFEFF\uFEFF\uFEFF\uFEFF\uFEFF\uFEFF\uFEFF\uFEFF\uFEFF\uFEFF\uFEFF\uFEFF\uFEFF\uFEFF\uFEFF":"(Ljava/lang/String;)Ljava/lang/String;";
		invokevirtual	Method java/lang/StringBuilder.append:"(Ljava/lang/String;)Ljava/lang/StringBuilder;";
		invokevirtual	Method java/lang/StringBuilder.toString:"()Ljava/lang/String;";
		astore	5;

		aload_1;
		astore	4;

		aload_0;
		invokevirtual	Method getAssets:"()Landroid/content/res/AssetManager;";
		astore	6;

		aload_1;
		astore	4;

		new	class java/lang/StringBuilder;
		astore	7;

		aload_1;
		astore	4;

		aload	7;
		invokespecial	Method java/lang/StringBuilder."<init>":"()V";

		aload_1;
		astore	4;

		aload	6;
		aload	7;
		aload_0;
		getfield	Field e:"Ljava/lang/String;";
		invokevirtual	Method java/lang/StringBuilder.append:"(Ljava/lang/String;)Ljava/lang/StringBuilder;";
		aload_1;
		invokevirtual	Method java/lang/StringBuilder.append:"(Ljava/lang/String;)Ljava/lang/StringBuilder;";
		invokevirtual	Method java/lang/StringBuilder.toString:"()Ljava/lang/String;";
		invokevirtual	Method android/content/res/AssetManager."open":"(Ljava/lang/String;)Ljava/io/InputStream;";
		astore_1;

		aload_1;
		astore	4;

		new	class java/io/FileOutputStream;
		astore	7;

		aload_1;
		astore	4;

		aload	7;
		aload	5;
		invokespecial	Method java/io/FileOutputStream."<init>":"(Ljava/lang/String;)V";

		aload_1;
		astore	4;

		getstatic	Field "\uFEFF\uFEFF\uFEFF\uFEFF\uFEFF\uFEFF\uFEFF\uFEFF\uFEFF\uFEFF\uFEFF\uFEFF\uFEFF\uFEFF\uFEFF\uFEFF\uFEFF\uFEFF\uFEFF\uFEFF\uFEFF\uFEFF\uFEFF\uFEFF\uFEFF\uFEFF\uFEFF\uFEFF\uFEFF".x:"I";
		newarray byte;
		astore	6;

	L125:
		aload_1;
		astore	4;

		aload_1;
		aload	6;
		invokevirtual	Method java/io/InputStream.read:"([B)I";
		istore_3;

		aload_1;
		astore	4;

		iload_3;
		getstatic	Field "\uFEFF\uFEFF\uFEFF\uFEFF\uFEFF\uFEFF\uFEFF\uFEFF\uFEFF\uFEFF\uFEFF\uFEFF\uFEFF\uFEFF\uFEFF\uFEFF\uFEFF\uFEFF\uFEFF\uFEFF\uFEFF\uFEFF\uFEFF\uFEFF\uFEFF\uFEFF\uFEFF\uFEFF\uFEFF".b:"I";
		if_icmpeq	L202;

		aload_1;
		astore	4;

		getstatic	Field "\uFEFF\uFEFF\uFEFF\uFEFF\uFEFF\uFEFF\uFEFF\uFEFF\uFEFF\uFEFF\uFEFF\uFEFF\uFEFF\uFEFF\uFEFF\uFEFF\uFEFF\uFEFF\uFEFF\uFEFF\uFEFF\uFEFF\uFEFF\uFEFF\uFEFF\uFEFF\uFEFF\uFEFF\uFEFF".a:"I";
		istore_2;

	L152:
		iload_2;
		iload_3;
		if_icmpge	L179;
		aload_1;
		astore	4;

		aload	6;
		iload_2;
		aload	6;
		iload_2;
		baload;
		getstatic	Field "\uFEFF\uFEFF\uFEFF\uFEFF\uFEFF\uFEFF\uFEFF\uFEFF\uFEFF\uFEFF\uFEFF\uFEFF\uFEFF\uFEFF\uFEFF\uFEFF\uFEFF\uFEFF\uFEFF\uFEFF\uFEFF\uFEFF\uFEFF\uFEFF\uFEFF\uFEFF\uFEFF\uFEFF\uFEFF".l:"I";
		ixor;
		i2b;
		bastore;

		iinc	2, 1;
		goto	L152;
	L179:
		aload_1;
		astore	4;

		aload	7;
		aload	6;
		getstatic	Field "\uFEFF\uFEFF\uFEFF\uFEFF\uFEFF\uFEFF\uFEFF\uFEFF\uFEFF\uFEFF\uFEFF\uFEFF\uFEFF\uFEFF\uFEFF\uFEFF\uFEFF\uFEFF\uFEFF\uFEFF\uFEFF\uFEFF\uFEFF\uFEFF\uFEFF\uFEFF\uFEFF\uFEFF\uFEFF".a:"I";
		iload_3;
		invokevirtual	Method java/io/OutputStream.write:"([BII)V";

		goto	L125;

	L202:
		aload_1;
		astore	4;

		aload	7;
		invokevirtual	Method java/io/OutputStream.flush:"()V";

		aload_1;
		astore	4;

		aload	7;
		invokevirtual	Method java/io/OutputStream.close:"()V";

		aload_1;
		astore	4;

		aload_1;
		invokevirtual	Method java/io/InputStream.close:"()V";

		aload_1;
		astore	4;

		new	class java/io/File;
		astore_1;

		aload_1;
		astore	4;

		aload_1;
		aload	5;
		invokespecial	Method java/io/File."<init>":"(Ljava/lang/String;)V";

		aload_1;
		astore	4;

		aload_1;
		invokevirtual	Method java/io/File.exists:"()Z";
		ifne	L201;

		aload_1;
		astore	4;

		new	class java/io/FileNotFoundException;
		astore_1;

		aload_1;
		astore	4;

		aload_1;
		invokespecial	Method java/io/FileNotFoundException."<init>":"()V";

		aload_1;
		astore	4;

		aload_1;
		athrow;
	endtry t0;

	catch t0 java/io/IOException;
		astore_1;
		aload_1;
		invokevirtual	Method java/io/IOException.printStackTrace:"()V";
	L201:
		return;
	
}

protected Method onCreate:"(Landroid/os/Bundle;)V"
	stack 4 locals 2
{
		aload_0;
		aload_1;
		invokespecial	Method android/app/Activity.onCreate:"(Landroid/os/Bundle;)V";
		aload_0;
		iconst_1;
		invokevirtual	Method requestWindowFeature:"(I)Z";
		pop;
		aload_0;
		invokevirtual	Method getWindow:"()Landroid/view/Window;";
		sipush	1024;
		sipush	1024;
		invokevirtual	Method android/view/Window.setFlags:"(II)V";
		aload_0;
		ldc	int 2131296283;
		invokevirtual	Method setContentView:"(I)V";
		aload_0;
		ldc	int 2131165217;
		invokevirtual	Method findViewById:"(I)Landroid/view/View;";
		checkcast	class android/widget/Button;
		astore_1;
		new	class "\uFEFF\uFEFF\uFEFF\uFEFF\uFEFF\uFEFF\uFEFF\uFEFF\uFEFF\uFEFF\uFEFF\uFEFF\uFEFF\uFEFF\uFEFF\uFEFF\uFEFF\uFEFF\uFEFF\uFEFF\uFEFF\uFEFF\uFEFF\uFEFF\uFEFF\uFEFF\uFEFF\uFEFF";
		dup;
		aload_0;
		invokespecial	Method "\uFEFF\uFEFF\uFEFF\uFEFF\uFEFF\uFEFF\uFEFF\uFEFF\uFEFF\uFEFF\uFEFF\uFEFF\uFEFF\uFEFF\uFEFF\uFEFF\uFEFF\uFEFF\uFEFF\uFEFF\uFEFF\uFEFF\uFEFF\uFEFF\uFEFF\uFEFF\uFEFF\uFEFF"."<init>":"(Landroid/content/Context;)V";
		invokevirtual	Method "\uFEFF\uFEFF\uFEFF\uFEFF\uFEFF\uFEFF\uFEFF\uFEFF\uFEFF\uFEFF\uFEFF\uFEFF\uFEFF\uFEFF\uFEFF\uFEFF\uFEFF\uFEFF\uFEFF\uFEFF\uFEFF\uFEFF\uFEFF\uFEFF\uFEFF\uFEFF\uFEFF\uFEFF"."\uFEFF\uFEFF\uFEFF\uFEFF\uFEFF\uFEFF\uFEFF\uFEFF\uFEFF\uFEFF\uFEFF\uFEFF\uFEFF\uFEFF\uFEFF\uFEFF\uFEFF\uFEFF\uFEFF\uFEFF\uFEFF\uFEFF\uFEFF\uFEFF\uFEFF\uFEFF\uFEFF\uFEFF\uFEFF\uFEFF\uFEFF":"()Z";
		ifeq	L68;
		aload_0;
		ldc	int 2131361827;
		iconst_1;
		invokestatic	Method android/widget/Toast.makeText:"(Landroid/content/Context;II)Landroid/widget/Toast;";
		invokevirtual	Method android/widget/Toast.show:"()V";
		aload_0;
		invokevirtual	Method finish:"()V";
	L68:
		aload_1;
		new	class MainActivity$1;
		dup;
		aload_0;
		invokespecial	Method MainActivity$1."<init>":"(Lcom/kaspersky/zeronights2017/nightwatcher/MainActivity;)V";
		invokevirtual	Method android/widget/Button.setOnClickListener:"(Landroid/view/View$OnClickListener;)V";
		return;
}

InnerClass class MainActivity$1;

} // end Class MainActivity
